Workbook

Sheet HOME
A1: GatiGo -- DCF Model Summary Dashboard
A2: One-page summary of the entire DCF model. All numbers link to their source sheets. Change any assumption -- this updates.
A3: Line Item | B3: FY 2026 | C3: FY 2027 | D3: FY 2028 | E3: Notes
A4: INCOME STATEMENT SUMMARY
A5: Total Revenue | B5: ='Income Statement'!B4 -> 8286207 | C5: ='Income Statement'!C4 -> 19200000 | D5: ='Income Statement'!D4 -> 38400000 | E5: FY26 = Rs 82.9L. FY27 = Rs 1.9Cr. FY28 = Rs 3.8Cr.
A6: Revenue Growth % | B6: "-" | C6: ='Income Statement'!C5 -> 1.3171036 | D6: ='Income Statement'!D5 -> 1 | E6: Strong growth driven by user scale and corporate partnerships.
A7: Gross Profit | B7: ='Income Statement'!B7 -> 132579.31 | C7: ='Income Statement'!C7 -> 4224000 | D7: ='Income Statement'!D7 -> 13440000 | E7: Thin margin in FY26 (1.6% -- actual Q1). Improves to 35% by FY28.
A8: EBITDA | B8: ='Income Statement'!B16 -> -17399421 | C8: ='Income Statement'!C16 -> -19776000 | D8: ='Income Statement'!D16 -> -17760000 | E8: Negative in FY26. Turns positive in FY27 as gross profit outgrows fixed costs.
A9: Net Profit / Loss | B9: ='Income Statement'!B23 -> -17675421 | C9: ='Income Statement'!C23 -> -20076000 | D9: ='Income Statement'!D23 -> -13545000 | E9: Loss in FY26 (Rs 1.8Cr full-year). Recovery path visible by FY28.
A10: CASH FLOW SUMMARY
A11: Operating Cash Flow | B11: ='Cash Flow'!B7 -> -17849421 | C11: ='Cash Flow'!C7 -> -20396000 | D11: ='Cash Flow'!D7 -> -14005000 | E11: Cash used or generated by operations each year.
A12: Free Cash Flow | B12: ='Cash Flow'!B12 -> -18089421 | C12: ='Cash Flow'!C12 -> -20996000 | D12: ='Cash Flow'!D12 -> -15205000 | E12: Cash available to investors. Used in the DCF valuation.
A13: Cumulative FCF | B13: ='Cash Flow'!B13 -> -18089421 | C13: ='Cash Flow'!C13 -> -39085421 | D13: ='Cash Flow'!D13 -> -54290421 | E13: Running cash position. Shows when business stops burning cash.
A14: DCF VALUATION SUMMARY
A15: Enterprise Value (EV) | B15: ='DCF Valuation'!B18 -> -74248024 | C15: "-" | D15: "-" | E15: Sum of discounted FCFs plus discounted Terminal Value. See DCF Valuation sheet for detail.
A16: Equity Value (EV minus Net Debt) | B16: ='DCF Valuation'!B20 -> -75748024 | C16: "-" | D16: "-" | E16: EV minus Rs 15L seed loan. What shareholders own.
A17: Value per Share (Rs) | B17: ='DCF Valuation'!B22 -> -75.748024 | C17: "-" | D17: "-" | E17: Equity Value divided by 1 million shares. Negative value means losses exceed terminal value at current assumptions.
A19: KEY ASSUMPTIONS USED IN THIS MODEL
A20: Assumption | B20: FY 2026 | C20: FY 2027 | D20: FY 2028 | E20: Meaning
A21: Gross Margin % | B21: =Assumptions!B7 -> 0.016 | C21: =Assumptions!C7 -> 0.22 | D21: =Assumptions!D7 -> 0.35 | E21: How much of each Rs 1 revenue stays after variable costs
A22: Discount Rate (WACC) | B22: =Assumptions!B18 -> 0.25 | C22: =Assumptions!C18 -> 0.25 | D22: =Assumptions!D18 -> 0.25 | E22: Risk rate. Higher = lower valuation
A23: Terminal Growth Rate | B23: =Assumptions!B19 -> 0.04 | C23: =Assumptions!C19 -> 0.04 | D23: =Assumptions!D19 -> 0.04 | E23: Growth assumed after Year 3 (forever)
A24: EBITDA Multiple | B24: =Assumptions!B20 -> 10 | C24: =Assumptions!C20 -> 10 | D24: =Assumptions!D20 -> 10 | E24: Backup valuation method
A25: Total Shares | B25: =Assumptions!B22 -> 1000000 | C25: =Assumptions!C22 -> 1000000 | D25: =Assumptions!D22 -> 1000000 | E25: Shares used to compute per-share value
A27: NOT a real startup. GatiGo is an academic design concept. All figures are hypothetical and for educational purposes only. | C27: Model by Anjani Kumar Mishra

Sheet Assumptions
A1: GatiGo - DCF Model Assumptions
A3: A Revenue Scale (annual totals -- FY 2026 = 4x Q1 annualised)
A4: Total Annual Revenue (Rs) | B4: 8286207 | C4: 19200000 | D4: 38400000 | E4: Rs | F4: FY26 = full-year forecast from Revenue Forecast file. FY27/28 = 2.3x and 2.0x growth.
A5: Revenue Growth Rate | B5: 0 | C5: 1.32 | D5: 1 | E5: % | F5: FY26 baseline. FY27 grows 132% (early stage scale-up). FY28 grows 100%.
A6: B Gross Margin and Cost Assumptions
A7: Gross Margin % | B7: 0.016 | C7: 0.22 | D7: 0.35 | E7: % | F7: FY26 = actual Q1 gross margin 1.6%. Improves as revenue scales over variable costs.
A8: Operating Expense -- Annual (Rs) | B8: 17532000 | C8: 24000000 | D8: 31200000 | E8: Rs | F8: FY26 = Q1 actual OpEx 1,461,000 x12. FY27/28 grow at 37% then 30% (hiring + infra).
A9: Depreciation -- Annual (Rs) | B9: 126000 | C9: 180000 | D9: 240000 | E9: Rs | F9: FY26 = Q1 actual 10,500 x12. Grows with new devices and equipment.
A10: Interest Expense -- Annual (Rs) | B10: 150000 | C10: 120000 | D10: 60000 | E10: Rs | F10: FY26 = Q1 actual 37,500 x4. Reduces as seed loan is partially repaid.
A11: C Tax
A12: Tax Rate | B12: 0 | C12: 0 | D12: 0.25 | E12: % | F12: 0% FY26 and FY27 -- losses carried forward. 25% FY28 if profitable (Indian corp tax).
A13: D Working Capital
A14: Change in Working Capital -- Annual (Rs) | B14: -300000 | C14: -500000 | D14: -700000 | E14: Rs | F14: Negative = cash tied up as business grows. More users = more prepaid marketing spend.
A15: E Capital Expenditure (CapEx)
A16: Capital Expenditure -- Annual (Rs) | B16: 240000 | C16: 600000 | D16: 1200000 | E16: Rs | F16: FY26 = laptops and devices (actual ~20K/mo). FY27 = server infra. FY28 = office build-out.
A17: F DCF Valuation Inputs
A18: Discount Rate (WACC) | B18: 0.25 | C18: 0.25 | D18: 0.25 | E18: % | F18: 25% is typical for early-stage Indian startups. Reflects high risk.
A19: Terminal Growth Rate | B19: 0.04 | C19: 0.04 | D19: 0.04 | E19: % | F19: 4% = long-run growth of Indian GDP. Applied after Year 3.
A20: Terminal Year EBITDA Multiple | B20: 10 | C20: 10 | D20: 10 | F20: 10x EBITDA is conservative for a growth-stage mobility app. BlaBlaCar traded at ~15x; QuickRide at ~8-12x.
A21: G Share Capital (for per-share valuation)
A22: Total Shares Outstanding | B22: 1000000 | C22: 1000000 | D22: 1000000 | E22: # | F22: 1 million shares assumed. Adjust to match actual cap table.
A24: NOT a real startup. GatiGo is an academic design concept. All figures are hypothetical and for educational purposes only. | D24: Model by Anjani Kumar Mishra

Sheet Income Statement
A1: GatiGo - 3-Year Income Statement (all amounts in Rs)
A3: REVENUE
A4: Total Revenue | B4: =Assumptions!B4 -> 8286207 | C4: =Assumptions!C4 -> 19200000 | D4: =Assumptions!D4 -> 38400000 | E4: Annual total. FY26 = full-year forecast from Revenue Forecast model.
A5: Revenue Growth % | B5: - | C5: =IFERROR((C4-B4)/B4,0) -> 1.3171036 | D5: =IFERROR((D4-C4)/C4,0) -> 1 | E5: Year-on-year growth. FY26 is the base year so no growth % shown.
A6: GROSS PROFIT
A7: Gross Profit | B7: =B4*Assumptions!B7 -> 132579.31 | C7: =C4*Assumptions!C7 -> 4224000 | D7: =D4*Assumptions!D7 -> 13440000 | E7: Revenue x Gross Margin %. Margin improves each year as scale reduces variable cost per ride.
A8: Gross Margin % | B8: =Assumptions!B7 -> 0.016 | C8: =Assumptions!C7 -> 0.22 | D8: =Assumptions!D7 -> 0.35 | E8: From Assumptions sheet. FY26 = 1.6% actual (Q1). Grows to 22% by FY27 as rides scale.
A9: OPERATING EXPENSES
A10: Total Operating Expenses | B10: =Assumptions!B8 -> 17532000 | C10: =Assumptions!C8 -> 24000000 | D10: =Assumptions!D8 -> 31200000 | E10: Q1 actual OpEx = Rs 1,461,000. Annualised and projected forward.
A11: Salaries (est. 50% of OpEx) | B11: =B10*0.5 -> 8766000 | C11: =C10*0.5 -> 12000000 | D11: =D10*0.5 -> 15600000 | E11: Q1 actual salaries = Rs 795,000 (54% of OpEx). Used 50% for simplicity.
A12: Marketing (est. 23% of OpEx) | B12: =B10*0.23 -> 4032360 | C12: =C10*0.23 -> 5520000 | D12: =D10*0.23 -> 7176000 | E12: Q1 actual marketing = Rs 330,000 (23% of OpEx). Matches actuals.
A13: Cloud and Infra (est. 8% of OpEx) | B13: =B10*0.08 -> 1402560 | C13: =C10*0.08 -> 1920000 | D13: =D10*0.08 -> 2496000 | E13: Q1 actual cloud = Rs 115,000 (7.9% of OpEx). Matches actuals.
A14: Other Fixed Costs (remaining 19%) | B14: =B10*0.19 -> 3331080 | C14: =C10*0.19 -> 4560000 | D14: =D10*0.19 -> 5928000 | E14: Office, legal, support, insurance, misc. Q1 actual = Rs 221,000.
A15: EBITDA
A16: EBITDA | B16: =B7-B10 -> -17399421 | C16: =C7-C10 -> -19776000 | D16: =D7-D10 -> -17760000 | E16: Gross Profit minus OpEx. FY26 is negative (early stage loss). Q1 actual EBITDA = Rs (14,46,041).
A17: EBITDA Margin % | B17: =IFERROR(B16/B4,0) -> -2.0998052 | C17: =IFERROR(C16/C4,0) -> -1.03 | D17: =IFERROR(D16/D4,0) -> -0.4625 | E17: EBITDA divided by Revenue. Negative in FY26. Improves as revenue scales.
A18: BELOW THE LINE
A19: Depreciation | B19: =Assumptions!B9 -> 126000 | C19: =Assumptions!C9 -> 180000 | D19: =Assumptions!D9 -> 240000 | E19: Q1 actual = Rs 10,500. Annualised to Rs 42,000. Grows with new assets.
A20: Interest Expense | B20: =Assumptions!B10 -> 150000 | C20: =Assumptions!C10 -> 120000 | D20: =Assumptions!D10 -> 60000 | E20: Q1 actual = Rs 37,500. Annualised to Rs 1,50,000. Reduces as loan repays.
A21: Earnings Before Tax (EBT) | B21: =B16-B19-B20 -> -17675421 | C21: =C16-C19-C20 -> -20076000 | D21: =D16-D19-D20 -> -18060000 | E21: EBITDA minus D&A minus Interest. Q1 actual = Rs (14,94,041).
A22: Tax | B22: =B21*Assumptions!B12 -> 0 | C22: =C21*Assumptions!C12 -> 0 | D22: =D21*Assumptions!D12 -> -4515000 | E22: Tax rate from Assumptions. 0% in FY26/27 due to loss carry-forward. 25% Indian corporate tax rate in FY28 if profitable.
A23: Net Profit / Loss | B23: =B21-B22 -> -17675421 | C23: =C21-C22 -> -20076000 | D23: =D21-D22 -> -13545000 | E23: Bottom line. Q1 actual net loss = Rs (14,94,041). FY26 full-year loss driven by high fixed costs vs early revenue.
A24: Net Margin % | B24: =IFERROR(B23/B4,0) -> -2.1331136 | C24: =IFERROR(C23/C4,0) -> -1.045625 | D24: =IFERROR(D23/D4,0) -> -0.35273437 | E24: Net Profit divided by Revenue.
A26: NOT a real startup. GatiGo is an academic design concept. All figures are hypothetical and for educational purposes only. | C26: Model by Anjani Kumar Mishra

Sheet Cash Flow
A1: GatiGo -- 3-Year Cash Flow Statement (amounts in Rs)
A2: Cash flow = how much actual cash the business generates or uses each year. Free Cash Flow (FCF) is used in the DCF valuation.
A3: PART 1 -- OPERATING CASH FLOW (cash from running the business)
A4: Net Profit / Loss | B4: ='Income Statement'!B23 -> -17675421 | C4: ='Income Statement'!C23 -> -20076000 | D4: ='Income Statement'!D23 -> -13545000 | E4: Starting point. Pulled from Income Statement.
A5: Add back: Depreciation | B5: ='Income Statement'!B19 -> 126000 | C5: ='Income Statement'!C19 -> 180000 | D5: ='Income Statement'!D19 -> 240000 | E5: Depreciation is a non-cash expense. We add it back because no cash left the business when we recorded it.
A6: Change in Working Capital | B6: =Assumptions!B14 -> -300000 | C6: =Assumptions!C14 -> -500000 | D6: =Assumptions!D14 -> -700000 | E6: Negative = cash used as business grows (more users = more upfront marketing and driver incentive payments).
A7: Operating Cash Flow | B7: =B4+B5+B6 -> -17849421 | C7: =C4+C5+C6 -> -20396000 | D7: =D4+D5+D6 -> -14005000 | E7: Cash actually generated (or used) by operations.
A8: PART 2 -- INVESTING CASH FLOW (cash spent on assets)
A9: Capital Expenditure (CapEx) | B9: =-Assumptions!B16 -> -240000 | C9: =-Assumptions!C16 -> -600000 | D9: =-Assumptions!D16 -> -1200000 | E9: Negative because spending cash. FY26 = devices and laptops. FY27 = server infra. FY28 = office build-out.
A10: Investing Cash Flow | B10: =B9 -> -240000 | C10: =C9 -> -600000 | D10: =D9 -> -1200000 | E10: Only CapEx for now. No acquisitions modelled.
A11: PART 3 -- FREE CASH FLOW (the number used in the DCF)
A12: Free Cash Flow (FCF) | B12: =B7+B10 -> -18089421 | C12: =C7+C10 -> -20996000 | D12: =D7+D10 -> -15205000 | E12: Operating Cash Flow + Investing Cash Flow. This is the cash available to investors. Used in the DCF calculation.
A13: Cumulative FCF | B13: =B12 -> -18089421 | C13: =B13+C12 -> -39085421 | D13: =C13+D12 -> -54290421 | E13: Running total of cash position. Shows when the business stops burning cash.
A15: NOT a real startup. GatiGo is an academic design concept. All figures are hypothetical and for educational purposes only. | C15: Model by Anjani Kumar Mishra

Sheet DCF Valuation
A1: GatiGo -- Discounted Cash Flow (DCF) Valuation
A3: STEP 1 -- Free Cash Flow (from Cash Flow sheet)
A4: Free Cash Flow (FCF) | B4: ='Cash Flow'!B12 -> -18089421 | C4: ='Cash Flow'!C12 -> -20996000 | D4: ='Cash Flow'!D12 -> -15205000 | E4: Pulled from Cash Flow sheet. This is the cash investors actually receive.
A5: STEP 2 -- Discount Rate (WACC)
A6: Discount Rate (WACC) | B6: =Assumptions!B18 -> 0.25 | C6: =Assumptions!C18 -> 0.25 | D6: =Assumptions!D18 -> 0.25 | E6: From Assumptions sheet. 25% = typical rate for high-risk early-stage startup.
A7: Year Number | B7: 1 | C7: 2 | D7: 3 | E7: Year 1 = FY2026. Year 2 = FY2027. Year 3 = FY2028.
A8: Discount Factor | B8: =1/(1+B6)^B7 -> 0.8 | C8: =1/(1+C6)^C7 -> 0.64 | D8: =1/(1+D6)^D7 -> 0.512 | E8: =1 / (1 + wacc) ^ year number. year 1 factor = 0.8. year 2 = 0.64. year 3 = 0.51. converts future cash to today's value.
A9: STEP 3 -- Present Value of Each Year's Cash Flow
A10: Present Value of FCF | B10: =B4*B8 -> -14471537 | C10: =C4*C8 -> -13437440 | D10: =D4*D8 -> -7784960 | E10: FCF x Discount Factor. This is how much each year's cash is worth in today's money.
A11: Sum of PV of FCF (Years 1-3) | B11: =B10+C10+D10 -> -35693937 | C11: "-" | D11: "-" | E11: Total of all three discounted cash flows. Shown in FY2026 column.
A12: STEP 4 -- Terminal Value (value of business after Year 3)
A13: Terminal Value -- Growth Method | B13: "-" | C13: "-" | D13: =D4*(1+Assumptions!B19)/(Assumptions!B18-Assumptions!B19) -> -75300952 | E13: =fcf year 3 x (1 + growth rate) / (wacc - growth rate). gordon growth model. assumes business grows at 4% forever after year 3
A14: Terminal Value -- EBITDA Multiple | B14: "-" | C14: "-" | D14: ='Income Statement'!D16*Assumptions!B20 -> -177600000 | E14: =year 3 ebitda x multiple from assumptions. if ebitda is negative in FY28, this gives a negative tv -- see note.
A15: Terminal Value Used (Growth Method) | B15: "-" | C15: "-" | D15: =D13 -> -75300952 | E15: Using Growth Method as primary. EBITDA Multiple shown for reference.
A16: PV of Terminal Value | B16: "-" | C16: "-" | D16: =D15*D8 -> -38554088 | E16: Terminal Value discounted back to today using Year 3 discount factor.
A17: STEP 5 -- Enterprise Value and Equity Value
A18: Enterprise Value (EV) | B18: =B11+D16 -> -74248024 | C18: "-" | D18: "-" | E18: =sum of discounted fcfs + discounted terminal value. this is the total value of the business.
A19: Seed Loan Outstanding (Net Debt) | B19: 1500000 | C19: "-" | D19: "-" | E19: Rs 15L seed loan (from Q1 actual assumptions -- loan at 10% p.a.). Subtract from EV to get Equity Value.
A20: Equity Value | B20: =B18-B19 -> -75748024 | C20: "-" | D20: "-" | E20: Enterprise Value minus Net Debt. This is what shareholders own.
A21: Shares Outstanding | B21: =Assumptions!B22 -> 1000000 | C21: "-" | D21: "-" | E21: From Assumptions sheet. 1 million shares assumed.
A22: Value per Share (Rs) | B22: =IFERROR(B20/B21,0) -> -75.748024 | C22: "-" | D22: "-" | E22: Equity Value divided by number of shares. Negative if losses outweigh terminal value -- means the model needs more revenue scale.
A23: STEP 6 -- Quick Sanity Check
A24: Revenue / EV Multiple (EV / FY28 Revenue) | B24: =IFERROR(B18/'Income Statement'!D4,0) -> -1.9335423 | C24: "-" | D24: "-" | E24: EV divided by FY2028 Revenue. A healthy growth startup trades at 2-5x revenue. If this is very negative, the terminal value is being dragged down by losses.
A25: EBITDA Multiple Check (EV / FY28 EBITDA) | B25: =IFERROR(B18/'Income Statement'!D16,0) -> 4.180632 | C25: "-" | D25: "-" | E25: EV divided by FY2028 EBITDA. Meaningful only if EBITDA is positive. Comparable: BlaBlaCar ~15x, QuickRide ~8-12x EBITDA.
A27: NOT a real startup. GatiGo is an academic design concept. All figures are hypothetical and for educational purposes only. | C27: Model by Anjani Kumar Mishra

Sheet Sensitivity Table
A1: GatiGo -- Sensitivity Analysis | How EV changes with WACC and Revenue
A3: TABLE A -- Enterprise Value (Rs) at different Discount Rates (WACC) and FY28 Revenue Multiples
A4: WACC (down) vs FY28 Revenue Multiple (across)
A5: WACC Rate | B5: Rev x0.5 | C5: Rev x0.75 | D5: Rev x1.0 | E5: Rev x1.25 | F5: Rev x1.5 | G5: Rev x2.0 | H5: Rev x2.5
A6: 15% | B6: =('Cash Flow'!B12/(1+0.15)^1)+('Cash Flow'!C12/(1+0.15)^2)+('Cash Flow'!D12*0.5/(1+0.15)^3)+(('Cash Flow'!D12*0.5*(1+0.04)/(0.15-0.04))/(1+0.15)^3) -> -83865762 | C6: =('Cash Flow'!B12/(1+0.15)^1)+('Cash Flow'!C12/(1+0.15)^2)+('Cash Flow'!D12*0.75/(1+0.15)^3)+(('Cash Flow'!D12*0.75*(1+0.04)/(0.15-0.04))/(1+0.15)^3) -> -1.0999568e+08 | D6: =('Cash Flow'!B12/(1+0.15)^1)+('Cash Flow'!C12/(1+0.15)^2)+('Cash Flow'!D12*1/(1+0.15)^3)+(('Cash Flow'!D12*1*(1+0.04)/(0.15-0.04))/(1+0.15)^3) -> -1.361256e+08 | E6: =('Cash Flow'!B12/(1+0.15)^1)+('Cash Flow'!C12/(1+0.15)^2)+('Cash Flow'!D12*1.25/(1+0.15)^3)+(('Cash Flow'!D12*1.25*(1+0.04)/(0.15-0.04))/(1+0.15)^3) -> -1.6225552e+08 | F6: =('Cash Flow'!B12/(1+0.15)^1)+('Cash Flow'!C12/(1+0.15)^2)+('Cash Flow'!D12*1.5/(1+0.15)^3)+(('Cash Flow'!D12*1.5*(1+0.04)/(0.15-0.04))/(1+0.15)^3) -> -1.8838544e+08 | G6: =('Cash Flow'!B12/(1+0.15)^1)+('Cash Flow'!C12/(1+0.15)^2)+('Cash Flow'!D12*2/(1+0.15)^3)+(('Cash Flow'!D12*2*(1+0.04)/(0.15-0.04))/(1+0.15)^3) -> -2.4064528e+08 | H6: =('Cash Flow'!B12/(1+0.15)^1)+('Cash Flow'!C12/(1+0.15)^2)+('Cash Flow'!D12*2.5/(1+0.15)^3)+(('Cash Flow'!D12*2.5*(1+0.04)/(0.15-0.04))/(1+0.15)^3) -> -2.9290512e+08
A7: 20% | B7: =('Cash Flow'!B12/(1+0.2)^1)+('Cash Flow'!C12/(1+0.2)^2)+('Cash Flow'!D12*0.5/(1+0.2)^3)+(('Cash Flow'!D12*0.5*(1+0.04)/(0.2-0.04))/(1+0.2)^3) -> -62652035 | C7: =('Cash Flow'!B12/(1+0.2)^1)+('Cash Flow'!C12/(1+0.2)^2)+('Cash Flow'!D12*0.75/(1+0.2)^3)+(('Cash Flow'!D12*0.75*(1+0.04)/(0.2-0.04))/(1+0.2)^3) -> -79150516 | D7: =('Cash Flow'!B12/(1+0.2)^1)+('Cash Flow'!C12/(1+0.2)^2)+('Cash Flow'!D12*1/(1+0.2)^3)+(('Cash Flow'!D12*1*(1+0.04)/(0.2-0.04))/(1+0.2)^3) -> -95648996 | E7: =('Cash Flow'!B12/(1+0.2)^1)+('Cash Flow'!C12/(1+0.2)^2)+('Cash Flow'!D12*1.25/(1+0.2)^3)+(('Cash Flow'!D12*1.25*(1+0.04)/(0.2-0.04))/(1+0.2)^3) -> -1.1214748e+08 | F7: =('Cash Flow'!B12/(1+0.2)^1)+('Cash Flow'!C12/(1+0.2)^2)+('Cash Flow'!D12*1.5/(1+0.2)^3)+(('Cash Flow'!D12*1.5*(1+0.04)/(0.2-0.04))/(1+0.2)^3) -> -1.2864596e+08 | G7: =('Cash Flow'!B12/(1+0.2)^1)+('Cash Flow'!C12/(1+0.2)^2)+('Cash Flow'!D12*2/(1+0.2)^3)+(('Cash Flow'!D12*2*(1+0.04)/(0.2-0.04))/(1+0.2)^3) -> -1.6164292e+08 | H7: =('Cash Flow'!B12/(1+0.2)^1)+('Cash Flow'!C12/(1+0.2)^2)+('Cash Flow'!D12*2.5/(1+0.2)^3)+(('Cash Flow'!D12*2.5*(1+0.04)/(0.2-0.04))/(1+0.2)^3) -> -1.9463988e+08
A8: 25% | B8: =('Cash Flow'!B12/(1+0.25)^1)+('Cash Flow'!C12/(1+0.25)^2)+('Cash Flow'!D12*0.5/(1+0.25)^3)+(('Cash Flow'!D12*0.5*(1+0.04)/(0.25-0.04))/(1+0.25)^3) -> -51078500 | C8: =('Cash Flow'!B12/(1+0.25)^1)+('Cash Flow'!C12/(1+0.25)^2)+('Cash Flow'!D12*0.75/(1+0.25)^3)+(('Cash Flow'!D12*0.75*(1+0.04)/(0.25-0.04))/(1+0.25)^3) -> -62663262 | D8: =('Cash Flow'!B12/(1+0.25)^1)+('Cash Flow'!C12/(1+0.25)^2)+('Cash Flow'!D12*1/(1+0.25)^3)+(('Cash Flow'!D12*1*(1+0.04)/(0.25-0.04))/(1+0.25)^3) -> -74248024 | E8: =('Cash Flow'!B12/(1+0.25)^1)+('Cash Flow'!C12/(1+0.25)^2)+('Cash Flow'!D12*1.25/(1+0.25)^3)+(('Cash Flow'!D12*1.25*(1+0.04)/(0.25-0.04))/(1+0.25)^3) -> -85832786 | F8: =('Cash Flow'!B12/(1+0.25)^1)+('Cash Flow'!C12/(1+0.25)^2)+('Cash Flow'!D12*1.5/(1+0.25)^3)+(('Cash Flow'!D12*1.5*(1+0.04)/(0.25-0.04))/(1+0.25)^3) -> -97417548 | G8: =('Cash Flow'!B12/(1+0.25)^1)+('Cash Flow'!C12/(1+0.25)^2)+('Cash Flow'!D12*2/(1+0.25)^3)+(('Cash Flow'!D12*2*(1+0.04)/(0.25-0.04))/(1+0.25)^3) -> -1.2058707e+08 | H8: =('Cash Flow'!B12/(1+0.25)^1)+('Cash Flow'!C12/(1+0.25)^2)+('Cash Flow'!D12*2.5/(1+0.25)^3)+(('Cash Flow'!D12*2.5*(1+0.04)/(0.25-0.04))/(1+0.25)^3) -> -1.437566e+08
A9: 30% | B9: =('Cash Flow'!B12/(1+0.3)^1)+('Cash Flow'!C12/(1+0.3)^2)+('Cash Flow'!D12*0.5/(1+0.3)^3)+(('Cash Flow'!D12*0.5*(1+0.04)/(0.3-0.04))/(1+0.3)^3) -> -43640610 | C9: =('Cash Flow'!B12/(1+0.3)^1)+('Cash Flow'!C12/(1+0.3)^2)+('Cash Flow'!D12*0.75/(1+0.3)^3)+(('Cash Flow'!D12*0.75*(1+0.04)/(0.3-0.04))/(1+0.3)^3) -> -52291612 | D9: =('Cash Flow'!B12/(1+0.3)^1)+('Cash Flow'!C12/(1+0.3)^2)+('Cash Flow'!D12*1/(1+0.3)^3)+(('Cash Flow'!D12*1*(1+0.04)/(0.3-0.04))/(1+0.3)^3) -> -60942613 | E9: =('Cash Flow'!B12/(1+0.3)^1)+('Cash Flow'!C12/(1+0.3)^2)+('Cash Flow'!D12*1.25/(1+0.3)^3)+(('Cash Flow'!D12*1.25*(1+0.04)/(0.3-0.04))/(1+0.3)^3) -> -69593614 | F9: =('Cash Flow'!B12/(1+0.3)^1)+('Cash Flow'!C12/(1+0.3)^2)+('Cash Flow'!D12*1.5/(1+0.3)^3)+(('Cash Flow'!D12*1.5*(1+0.04)/(0.3-0.04))/(1+0.3)^3) -> -78244616 | G9: =('Cash Flow'!B12/(1+0.3)^1)+('Cash Flow'!C12/(1+0.3)^2)+('Cash Flow'!D12*2/(1+0.3)^3)+(('Cash Flow'!D12*2*(1+0.04)/(0.3-0.04))/(1+0.3)^3) -> -95546619 | H9: =('Cash Flow'!B12/(1+0.3)^1)+('Cash Flow'!C12/(1+0.3)^2)+('Cash Flow'!D12*2.5/(1+0.3)^3)+(('Cash Flow'!D12*2.5*(1+0.04)/(0.3-0.04))/(1+0.3)^3) -> -1.1284862e+08
A10: 35% | B10: =('Cash Flow'!B12/(1+0.35)^1)+('Cash Flow'!C12/(1+0.35)^2)+('Cash Flow'!D12*0.5/(1+0.35)^3)+(('Cash Flow'!D12*0.5*(1+0.04)/(0.35-0.04))/(1+0.35)^3) -> -38376357 | C10: =('Cash Flow'!B12/(1+0.35)^1)+('Cash Flow'!C12/(1+0.35)^2)+('Cash Flow'!D12*0.75/(1+0.35)^3)+(('Cash Flow'!D12*0.75*(1+0.04)/(0.35-0.04))/(1+0.35)^3) -> -45104531 | D10: =('Cash Flow'!B12/(1+0.35)^1)+('Cash Flow'!C12/(1+0.35)^2)+('Cash Flow'!D12*1/(1+0.35)^3)+(('Cash Flow'!D12*1*(1+0.04)/(0.35-0.04))/(1+0.35)^3) -> -51832705 | E10: =('Cash Flow'!B12/(1+0.35)^1)+('Cash Flow'!C12/(1+0.35)^2)+('Cash Flow'!D12*1.25/(1+0.35)^3)+(('Cash Flow'!D12*1.25*(1+0.04)/(0.35-0.04))/(1+0.35)^3) -> -58560879 | F10: =('Cash Flow'!B12/(1+0.35)^1)+('Cash Flow'!C12/(1+0.35)^2)+('Cash Flow'!D12*1.5/(1+0.35)^3)+(('Cash Flow'!D12*1.5*(1+0.04)/(0.35-0.04))/(1+0.35)^3) -> -65289053 | G10: =('Cash Flow'!B12/(1+0.35)^1)+('Cash Flow'!C12/(1+0.35)^2)+('Cash Flow'!D12*2/(1+0.35)^3)+(('Cash Flow'!D12*2*(1+0.04)/(0.35-0.04))/(1+0.35)^3) -> -78745400 | H10: =('Cash Flow'!B12/(1+0.35)^1)+('Cash Flow'!C12/(1+0.35)^2)+('Cash Flow'!D12*2.5/(1+0.35)^3)+(('Cash Flow'!D12*2.5*(1+0.04)/(0.35-0.04))/(1+0.35)^3) -> -92201748
A13: Highlighted row = base WACC (25%). Highlighted column = base revenue (1.0x). The intersecting cell matches the DCF Valuation sheet Enterprise Value.
A15: TABLE B -- Enterprise Value (Rs) at different Terminal Growth Rates and WACC
A16: Terminal Growth Rate (down) vs WACC (across)
A17: Terminal Growth | B17: WACC 15% | C17: WACC 20% | D17: WACC 25% | E17: WACC 30% | F17: WACC 35%
A18: 2% | B18: =('Cash Flow'!B12/(1+0.15)^1)+('Cash Flow'!C12/(1+0.15)^2)+('Cash Flow'!D12/(1+0.15)^3)+(('Cash Flow'!D12*(1+0.02)/(0.15-0.02))/(1+0.15)^3) -> -1.2004565e+08 | C18: =('Cash Flow'!B12/(1+0.2)^1)+('Cash Flow'!C12/(1+0.2)^2)+('Cash Flow'!D12/(1+0.2)^3)+(('Cash Flow'!D12*(1+0.02)/(0.2-0.02))/(1+0.2)^3) -> -88316338 | D18: =('Cash Flow'!B12/(1+0.25)^1)+('Cash Flow'!C12/(1+0.25)^2)+('Cash Flow'!D12/(1+0.25)^3)+(('Cash Flow'!D12*(1+0.02)/(0.25-0.02))/(1+0.25)^3) -> -70218542 | E18: =('Cash Flow'!B12/(1+0.3)^1)+('Cash Flow'!C12/(1+0.3)^2)+('Cash Flow'!D12/(1+0.3)^3)+(('Cash Flow'!D12*(1+0.02)/(0.3-0.02))/(1+0.3)^3) -> -58470898 | F18: =('Cash Flow'!B12/(1+0.35)^1)+('Cash Flow'!C12/(1+0.35)^2)+('Cash Flow'!D12/(1+0.35)^3)+(('Cash Flow'!D12*(1+0.02)/(0.35-0.02))/(1+0.35)^3) -> -50201633
A19: 3% | B19: =('Cash Flow'!B12/(1+0.15)^1)+('Cash Flow'!C12/(1+0.15)^2)+('Cash Flow'!D12/(1+0.15)^3)+(('Cash Flow'!D12*(1+0.03)/(0.15-0.03))/(1+0.15)^3) -> -1.2741563e+08 | C19: =('Cash Flow'!B12/(1+0.2)^1)+('Cash Flow'!C12/(1+0.2)^2)+('Cash Flow'!D12/(1+0.2)^3)+(('Cash Flow'!D12*(1+0.03)/(0.2-0.03))/(1+0.2)^3) -> -91767001 | D19: =('Cash Flow'!B12/(1+0.25)^1)+('Cash Flow'!C12/(1+0.25)^2)+('Cash Flow'!D12/(1+0.25)^3)+(('Cash Flow'!D12*(1+0.03)/(0.25-0.03))/(1+0.25)^3) -> -72141704 | E19: =('Cash Flow'!B12/(1+0.3)^1)+('Cash Flow'!C12/(1+0.3)^2)+('Cash Flow'!D12/(1+0.3)^3)+(('Cash Flow'!D12*(1+0.03)/(0.3-0.03))/(1+0.3)^3) -> -59660983 | F19: =('Cash Flow'!B12/(1+0.35)^1)+('Cash Flow'!C12/(1+0.35)^2)+('Cash Flow'!D12/(1+0.35)^3)+(('Cash Flow'!D12*(1+0.03)/(0.35-0.03))/(1+0.35)^3) -> -50991683
A20: 4% | B20: =('Cash Flow'!B12/(1+0.15)^1)+('Cash Flow'!C12/(1+0.15)^2)+('Cash Flow'!D12/(1+0.15)^3)+(('Cash Flow'!D12*(1+0.04)/(0.15-0.04))/(1+0.15)^3) -> -1.361256e+08 | C20: =('Cash Flow'!B12/(1+0.2)^1)+('Cash Flow'!C12/(1+0.2)^2)+('Cash Flow'!D12/(1+0.2)^3)+(('Cash Flow'!D12*(1+0.04)/(0.2-0.04))/(1+0.2)^3) -> -95648996 | D20: =('Cash Flow'!B12/(1+0.25)^1)+('Cash Flow'!C12/(1+0.25)^2)+('Cash Flow'!D12/(1+0.25)^3)+(('Cash Flow'!D12*(1+0.04)/(0.25-0.04))/(1+0.25)^3) -> -74248024 | E20: =('Cash Flow'!B12/(1+0.3)^1)+('Cash Flow'!C12/(1+0.3)^2)+('Cash Flow'!D12/(1+0.3)^3)+(('Cash Flow'!D12*(1+0.04)/(0.3-0.04))/(1+0.3)^3) -> -60942613 | F20: =('Cash Flow'!B12/(1+0.35)^1)+('Cash Flow'!C12/(1+0.35)^2)+('Cash Flow'!D12/(1+0.35)^3)+(('Cash Flow'!D12*(1+0.04)/(0.35-0.04))/(1+0.35)^3) -> -51832705
A21: 5% | B21: =('Cash Flow'!B12/(1+0.15)^1)+('Cash Flow'!C12/(1+0.15)^2)+('Cash Flow'!D12/(1+0.15)^3)+(('Cash Flow'!D12*(1+0.05)/(0.15-0.05))/(1+0.15)^3) -> -1.4657757e+08 | C21: =('Cash Flow'!B12/(1+0.2)^1)+('Cash Flow'!C12/(1+0.2)^2)+('Cash Flow'!D12/(1+0.2)^3)+(('Cash Flow'!D12*(1+0.05)/(0.2-0.05))/(1+0.2)^3) -> -1.0004859e+08 | D21: =('Cash Flow'!B12/(1+0.25)^1)+('Cash Flow'!C12/(1+0.25)^2)+('Cash Flow'!D12/(1+0.25)^3)+(('Cash Flow'!D12*(1+0.05)/(0.25-0.05))/(1+0.25)^3) -> -76564977 | E21: =('Cash Flow'!B12/(1+0.3)^1)+('Cash Flow'!C12/(1+0.3)^2)+('Cash Flow'!D12/(1+0.3)^3)+(('Cash Flow'!D12*(1+0.05)/(0.3-0.05))/(1+0.3)^3) -> -62326773 | F21: =('Cash Flow'!B12/(1+0.35)^1)+('Cash Flow'!C12/(1+0.35)^2)+('Cash Flow'!D12/(1+0.35)^3)+(('Cash Flow'!D12*(1+0.05)/(0.35-0.05))/(1+0.35)^3) -> -52729795
A22: 6% | B22: =('Cash Flow'!B12/(1+0.15)^1)+('Cash Flow'!C12/(1+0.15)^2)+('Cash Flow'!D12/(1+0.15)^3)+(('Cash Flow'!D12*(1+0.06)/(0.15-0.06))/(1+0.15)^3) -> -1.593522e+08 | C22: =('Cash Flow'!B12/(1+0.2)^1)+('Cash Flow'!C12/(1+0.2)^2)+('Cash Flow'!D12/(1+0.2)^3)+(('Cash Flow'!D12*(1+0.06)/(0.2-0.06))/(1+0.2)^3) -> -1.050767e+08 | D22: =('Cash Flow'!B12/(1+0.25)^1)+('Cash Flow'!C12/(1+0.25)^2)+('Cash Flow'!D12/(1+0.25)^3)+(('Cash Flow'!D12*(1+0.06)/(0.25-0.06))/(1+0.25)^3) -> -79125819 | E22: =('Cash Flow'!B12/(1+0.3)^1)+('Cash Flow'!C12/(1+0.3)^2)+('Cash Flow'!D12/(1+0.3)^3)+(('Cash Flow'!D12*(1+0.06)/(0.3-0.06))/(1+0.3)^3) -> -63826280 | F22: =('Cash Flow'!B12/(1+0.35)^1)+('Cash Flow'!C12/(1+0.35)^2)+('Cash Flow'!D12/(1+0.35)^3)+(('Cash Flow'!D12*(1+0.06)/(0.35-0.06))/(1+0.35)^3) -> -53688753
A25: Highlighted row = base terminal growth rate (4%). Highlighted column = base WACC (25%).
A27: NOT a real startup. GatiGo is an academic design concept. All figures are hypothetical and for educational purposes only. | E27: Model by Anjani Kumar Mishra

Sheet Notes
A1: GatiGo -- DCF Model Notes, Methodology and Limitations
B2: What is a DCF? | C2: A Discounted Cash Flow (DCF) model estimates what a business is worth today, based on the cash it is expected to generate in the future. Future cash is worth less than cash today (because of risk and inflation), so we discount it back using a rate called WACC.
B3: What is WACC? | C3: WACC stands for Weighted Average Cost of Capital. It represents the minimum return investors expect for the risk they are taking. For an early-stage startup like GatiGo, 25% is used -- much higher than a stable company (which might use 8-12%) because the risk of failure is higher.
B4: What is Terminal Value? | C4: A 3-year model only captures 3 years of cash flows. But a business (if successful) keeps generating cash beyond Year 3. The Terminal Value captures all that future value in one number. We used the Gordon Growth Model: TV = FCF x (1+g) / (WACC - g).
B5: Why is EV sometimes negative? | C5: When a startup has large losses and small revenues in early years, the discounted losses can outweigh the discounted terminal value. This does not mean the business is worthless -- it means the model needs better revenue growth assumptions, or a longer projection period, or a lower discount rate. Real VC investors use 5-10 year models.
B6: Q1 Anchor Values | C6: FY 2026 inputs are anchored to Q1 actual results from GatiGo_Clean_Dashboard.xlsx: Total Q1 Revenue = Rs 9,25,879 Total Q1 EBITDA = Rs (14,46,041) Total Q1 Net Loss = Rs (14,94,041) Total Q1 Rides = 15,460 Gross Margin Q1 = 1.6% Full-year FY2026 = derived from Revenue Forecast model (Rs 82.86L total revenue).
B7: Key Limitations | C7: 1. This model has only 3 years. Real DCF models use 5-10 years for startups. 2. Working capital and CapEx are estimated -- actual figures would need detailed planning. 3. The model does not account for new funding rounds that would dilute shares. 4. Tax loss carry-forward is assumed but not modelled in detail. 5. All figures are for an academic project -- not a real business.
B8: Author and Disclaimer | C8: Model by Anjani Kumar Mishra Portfolio: https://inakm.github.io LinkedIn: https://www.linkedin.com/in/inakmm Project: https://inakm.github.io/page/projects/gatigo.html NOT a real startup. GatiGo is an academic design concept. All financial figures are completely made up for educational purposes only.
B10: Model by Anjani Kumar Mishra
