Workbook

Sheet Income_Data
A1: Year | B1: Revenue | C1: COGS | D1: SG&A | E1: R&D | F1: Depreciation | G1: Interest Expense | H1: Tax Rate | I1: EBIT | J1: NOPAT
A2: 2020 | B2: 1250 | C2: 720 | D2: 180 | E2: 95 | F2: 60 | G2: 40 | H2: 0.25 | I2: =B2-C2-D2-E2-F2 -> 195 | J2: =I2*(1-H2) -> 146.25
A3: 2021 | B3: 1380 | C3: 790 | D3: 205 | E3: 110 | F3: 72 | G3: 45 | H3: 0.26 | I3: =B3-C3-D3-E3-F3 -> 203 | J3: =I3*(1-H3) -> 150.22
A4: 2022 | B4: 1525 | C4: 860 | D4: 240 | E4: 125 | F4: 85 | G4: 48 | H4: 0.27 | I4: =B4-C4-D4-E4-F4 -> 215 | J4: =I4*(1-H4) -> 156.95
A5: 2023 | B5: 1680 | C5: 940 | D5: 260 | E5: 140 | F5: 95 | G5: 52 | H5: 0.27 | I5: =B5-C5-D5-E5-F5 -> 245 | J5: =I5*(1-H5) -> 178.85
A6: 2024 | B6: 1850 | C6: 1030 | D6: 295 | E6: 160 | F6: 110 | G6: 55 | H6: 0.28 | I6: =B6-C6-D6-E6-F6 -> 255 | J6: =I6*(1-H6) -> 183.6

Sheet Balance_Data
A1: Year | B1: Cash | C1: Accounts Receivable | D1: Inventory | E1: Accounts Payable | F1: Debt | G1: Equity | H1: WC | I1: ΔWC
A2: 2020 | B2: 150 | C2: 210 | D2: 180 | E2: 160 | F2: 500 | G2: 600 | H2: =C2+D2-E2 -> 230 | I2: 0
A3: 2021 | B3: 165 | C3: 230 | D3: 200 | E3: 175 | F3: 540 | G3: 640 | H3: =C3+D3-E3 -> 255 | I3: =H3-H2 -> 25
A4: 2022 | B4: 180 | C4: 255 | D4: 225 | E4: 190 | F4: 580 | G4: 690 | H4: =C4+D4-E4 -> 290 | I4: =H4-H3 -> 35
A5: 2023 | B5: 200 | C5: 275 | D5: 250 | E5: 210 | F5: 620 | G5: 740 | H5: =C5+D5-E5 -> 315 | I5: =H5-H4 -> 25
A6: 2024 | B6: 220 | C6: 300 | D6: 280 | E6: 230 | F6: 660 | G6: 800 | H6: =C6+D6-E6 -> 350 | I6: =H6-H5 -> 35

Sheet Drivers
A1: Year | B1: CapEx | C1: =Balance_Data!I1 -> ΔWC | D1: =Income_Data!J1 -> NOPAT | E1: =Income_Data!F1 -> Depreciation | F1: FCF | G1: DF | H1: PV
A2: 2020 | B2: 120 | C2: =Balance_Data!I2 -> 0 | D2: =Income_Data!J2 -> 146.25 | E2: =Income_Data!F2 -> 60 | F2: =D2+E2-B2-C2 -> 86.25 | G2: =1/(1+Market_Assumptions!B16)^1 -> 0.8997013 | H2: =F2*G2 -> 77.599237
A3: 2021 | B3: 140 | C3: =Balance_Data!I3 -> 25 | D3: =Income_Data!J3 -> 150.22 | E3: =Income_Data!F3 -> 72 | F3: =D3+E3-B3-C3 -> 57.22 | G3: =1/(1+Market_Assumptions!B16)^2 -> 0.80946243 | H3: =F3*G3 -> 46.31744
A4: 2022 | B4: 165 | C4: =Balance_Data!I4 -> 35 | D4: =Income_Data!J4 -> 156.95 | E4: =Income_Data!F4 -> 85 | F4: =D4+E4-B4-C4 -> 41.95 | G4: =1/(1+Market_Assumptions!B16)^3 -> 0.7282744 | H4: =F4*G4 -> 30.551111
A5: 2023 | B5: 190 | C5: =Balance_Data!I5 -> 25 | D5: =Income_Data!J5 -> 178.85 | E5: =Income_Data!F5 -> 95 | F5: =D5+E5-B5-C5 -> 58.85 | G5: =1/(1+Market_Assumptions!B16)^4 -> 0.65522942 | H5: =F5*G5 -> 38.560251
A6: 2024 | B6: 210 | C6: =Balance_Data!I6 -> 35 | D6: =Income_Data!J6 -> 183.6 | E6: =Income_Data!F6 -> 110 | F6: =D6+E6-B6-C6 -> 48.6 | G6: =1/(1+Market_Assumptions!B16)^5 -> 0.58951076 | H6: =F6*G6 -> 28.650223

Sheet Market_Assumptions
A1: Parameter | B1: Value
A2: Risk Free Rate | B2: 0.07
A3: Equity Risk Premium | B3: 0.06
A4: Beta | B4: 1.25
A5: Cost of Debt | B5: 0.085
A6: Tax Rate (use marginal) | B6: 0.28
A7: Target Debt % | B7: 0.4
A8: Target Equity % | B8: 0.6
A9: Terminal Growth Rate | B9: 0.035
A12: Cost of Capital (WACC)
A13: Cost of Equity (CAPM) | B13: =B2+B4*B3 -> 0.145
A14: After Tax Cost of Debt | B14: =B5*(1-B6) -> 0.0612
A16: WACC | B16: =(B8*B13)+(B7*B14) -> 0.11148
