Workbook

Sheet Assumptions
A1: Rail Vikas Nigam Limited - Model Assumptions
A2: Units: INR Crore | Source: RVNL Annual Report FY2025
A4: Particulars | B4: FY2024A | C4: FY2025A | D4: FY2026E | E4: FY2027E
A5: Income Statement Assumptions
A6: Revenue from Operations (INR Cr) | B6: 21732.58 | C6: 19869.35
A7: Revenue Growth % | D7: 0.05 | E7: 0.08
A8: Other Income (INR Cr) | B8: 1182.55 | C8: 1018.89
A9: Expenditure on Operations % of Revenue | B9: Derived from P&L | C9: Derived from P&L
A10: Employee Benefit Expense (INR Cr) | B10: 184.18 | C10: 182.98
A11: Employee Growth % | D11: 0.04 | E11: 0.04
A12: Finance Costs (INR Cr) | B12: 568.49 | C12: 539.51
A13: Finance Cost Growth % | D13: -0.05 | E13: -0.05
A14: Depreciation (INR Cr) | B14: 20.82 | C14: 30.6
A15: Depreciation Growth % | D15: 0.08 | E15: 0.08
A16: Other Expenses (INR Cr) | B16: 161 | C16: 199.78
A17: Other Expenses Growth % | D17: 0.05 | E17: 0.05
A18: Effective Tax Rate % | D18: 0.233 | E18: 0.233
A20: Balance Sheet / Working Capital Assumptions
A21: Days Receivable (Trade) | D21: 27 | E21: 27
A22: Capex (INR Cr) | B22: 116.17 | C22: 431.63 | D22: 250 | E22: 220
A23: Long-term Borrowings Repayment (INR Cr) | B23: 377.29 | C23: 472 | D23: 472 | E23: 400
A24: Dividend Payout (INR Cr) | B24: 439.94 | C24: 358.62 | D24: 358.62 | E24: 400
A27: Color Legend:
A28: Blue = Hardcoded Input
A29: Black = Formula / Calculated
A30: Green = Cross-sheet Link

Sheet Income Statement
A1: Rail Vikas Nigam Limited - Income Statement
A2: Units: INR Crore | Source: Standalone Financial Statements
A4: Particulars | B4: FY2024A | C4: FY2025A | D4: FY2026E | E4: FY2027E
A5: Revenue
A6: Revenue from Operations | B6: =Assumptions!B6 -> 21732.58 | C6: =Assumptions!C6 -> 19869.35 | D6: =C6*(1+Assumptions!D7) -> 20862.818 | E6: =D6*(1+Assumptions!E7) -> 22531.843
A7: Other Income | B7: =Assumptions!B8 -> 1182.55 | C7: =Assumptions!C8 -> 1018.89 | D7: =C7*0.95 -> 967.9455 | E7: =D7*0.95 -> 919.54822
A8: Total Income | B8: =SUM(B6:B7) -> 22915.13 | C8: =SUM(C6:C7) -> 20888.24 | D8: =SUM(D6:D7) -> 21830.763 | E8: =SUM(E6:E7) -> 23451.391
A9: Expenses
A10: Expenditure on Operations | B10: 20041.24 | C10: 18385.2 | D10: =D6*(C10/C6) -> 19304.46 | E10: =E6*(C10/C6) -> 20848.817
A11: Employee Benefits Expense | B11: =Assumptions!B10 -> 184.18 | C11: =Assumptions!C10 -> 182.98 | D11: =C11*(1+Assumptions!D11) -> 190.2992 | E11: =D11*(1+Assumptions!E11) -> 197.91117
A12: Finance Costs | B12: =Assumptions!B12 -> 568.49 | C12: =Assumptions!C12 -> 539.51 | D12: =C12*(1+Assumptions!D13) -> 512.5345 | E12: =D12*(1+Assumptions!E13) -> 486.90777
A13: Depreciation and Amortisation | B13: =Assumptions!B14 -> 20.82 | C13: =Assumptions!C14 -> 30.6 | D13: =C13*(1+Assumptions!D15) -> 33.048 | E13: =D13*(1+Assumptions!E15) -> 35.69184
A14: Other Expenses | B14: =Assumptions!B16 -> 161 | C14: =Assumptions!C16 -> 199.78 | D14: =C14*(1+Assumptions!D17) -> 209.769 | E14: =D14*(1+Assumptions!E17) -> 220.25745
A15: Total Expenses | B15: =SUM(B10:B14) -> 20975.73 | C15: =SUM(C10:C14) -> 19338.07 | D15: =SUM(D10:D14) -> 20250.111 | E15: =SUM(E10:E14) -> 21789.585
A16: Key Metrics
A17: EBITDA (PBT + Finance Costs + Dep) | B17: =B8-B10-B11-B14 -> 2528.71 | C17: =C8-C10-C11-C14 -> 2120.28 | D17: =D8-D10-D11-D14 -> 2126.2348 | E17: =E8-E10-E11-E14 -> 2184.4057
A18: EBITDA Margin % | B18: =B17/B6 -> 0.11635572 | C18: =C17/C6 -> 0.10671109 | D18: =D17/D6 -> 0.10191504 | E18: =E17/E6 -> 0.096947494
A19: Profit Before Tax (PBT) | B19: =B8-B15 -> 1939.4 | C19: =C8-C15 -> 1550.17 | D19: =D8-D15 -> 1580.6523 | E19: =E8-E15 -> 1661.8061
A20: PBT Margin % | B20: =B19/B6 -> 0.08923929 | C20: =C19/C6 -> 0.078018154 | D20: =D19/D6 -> 0.075764086 | E20: =E19/E6 -> 0.073753669
A21: Tax Expense | B21: 476.45 | C21: 361.55 | D21: =D19*Assumptions!D18 -> 368.29199 | E21: =E19*Assumptions!E18 -> 387.20082
A22: Profit After Tax (PAT) | B22: =B19-B21 -> 1462.95 | C22: =C19-C21 -> 1188.62 | D22: =D19-D21 -> 1212.3603 | E22: =E19-E21 -> 1274.6053
A23: PAT Margin % | B23: =B22/B6 -> 0.067315984 | C23: =C22/C6 -> 0.059821786 | D23: =D22/D6 -> 0.058111054 | E23: =E22/E6 -> 0.056569064
A24: Other Comprehensive Income (OCI) | B24: 0.24 | C24: 7.77 | D24: 5 | E24: 5
A25: Total Comprehensive Income | B25: =B22+B24 -> 1463.19 | C25: =C22+C24 -> 1196.39 | D25: =D22+D24 -> 1217.3603 | E25: =E22+E24 -> 1279.6053
A26: Per Share Data (shares: 2,08,50,20,100)
A27: EPS - Basic (Rs.) | B27: 7.0164791 | C27: 5.7007604 | D27: =D22*10000000/2085020100 -> 5.8146217 | E27: =E22*10000000/2085020100 -> 6.1131558
A28: DPS - Dividend per Share (Rs.) | B28: 2.11 | C28: 1.72 | D28: 1.72 | E28: 1.92

Sheet Balance Sheet
A1: Rail Vikas Nigam Limited - Balance Sheet
A2: Units: INR Crore | Source: Standalone Balance Sheet as at 31 March 2025
A4: Particulars | B4: FY2024A | C4: FY2025A | D4: FY2026E | E4: FY2027E
A5: ASSETS
A6: Non-Current Assets
A7: Property, Plant and Equipment | B7: 28.62 | C7: 537.21 | D7: =C7+Assumptions!D23-'Income Statement'!D13 -> 976.162 | E7: =D7+Assumptions!E23-'Income Statement'!E13 -> 1340.4702
A8: Right-of-Use Assets | B8: 328.88 | C8: 346.13 | D8: 330 | E8: 315
A9: Investments (Non-Current) | B9: 1610.75 | C9: 1764.13 | D9: 1900 | E9: 2000
A10: Lease Receivables (Non-Current) | B10: 4492.36 | C10: 3992.85 | D10: 3500 | E10: 3000
A11: Other Non-Current Assets | B11: 2512.32 | C11: 1375.37 | D11: 1300 | E11: 1250
A12: Total Non-Current Assets | B12: =SUM(B7:B11) -> 8972.93 | C12: =SUM(C7:C11) -> 8015.69 | D12: =SUM(D7:D11) -> 8006.162 | E12: =SUM(E7:E11) -> 7905.4702
A13: Current Assets
A14: Trade Receivables | B14: 1106.48 | C14: 1489.51 | D14: ='Income Statement'!D6/365*Assumptions!D22 -> 14289.601 | E14: ='Income Statement'!E6/365*Assumptions!E22 -> 13580.837
A15: Cash and Cash Equivalents | B15: 1027.49 | C15: 3044.8 | D15: ='Cash Flow'!D25 -> 0 | E15: ='Cash Flow'!E25 -> 0
A16: Other Current Assets (incl. Bank Bal) | B16: 7532.63 | C16: 6938.19 | D16: 6600 | E16: 6300
A17: Total Current Assets | B17: =SUM(B14:B16) -> 9666.6 | C17: =SUM(C14:C16) -> 11472.5 | D17: =SUM(D14:D16) -> 20889.601 | E17: =SUM(E14:E16) -> 19880.837
A18: TOTAL ASSETS | B18: =B12+B17 -> 18639.53 | C18: =C12+C17 -> 19488.19 | D18: =D12+D17 -> 28895.763 | E18: =E12+E17 -> 27786.307
A19: EQUITY AND LIABILITIES
A20: Equity
A21: Share Capital | B21: 2085.02 | C21: 2085.02 | D21: 2085.02 | E21: 2085.02
A22: Reserves and Surplus | B22: 5782.26 | C22: 6538.7 | D22: =C22+'Income Statement'!D22+'Income Statement'!D24-Assumptions!D25 -> 7756.0603 | E22: =D22+'Income Statement'!E22+'Income Statement'!E24-Assumptions!E25 -> 9035.6656
A23: Total Equity | B23: =B21+B22 -> 7867.28 | C23: =C21+C22 -> 8623.72 | D23: =D21+D22 -> 9841.0803 | E23: =E21+E22 -> 11120.686
A24: Non-Current Liabilities
A25: Long-Term Borrowings (IRFC) | B25: 5515.77 | C25: 4889.51 | D25: =C25-Assumptions!D24 -> 4530.89 | E25: =D25-Assumptions!E24 -> 4130.89
A26: Other Non-Current Liabilities | B26: 769.31 | C26: 362.99 | D26: 340 | E26: 320
A27: Total Non-Current Liabilities | B27: =B25+B26 -> 6285.08 | C27: =C25+C26 -> 5252.5 | D27: =D25+D26 -> 4870.89 | E27: =E25+E26 -> 4450.89
A28: Current Liabilities
A29: Current Borrowings | B29: 472 | C29: 499.51 | D29: 472 | E29: 400
A30: Trade Payables | B30: 252.4 | C30: 344.87 | D30: 360 | E30: 375
A31: Other Current Liabilities | B31: 3858.1 | C31: 4763.61 | D31: 4800 | E31: 4850
A32: Total Current Liabilities | B32: =SUM(B29:B31) -> 4582.5 | C32: =SUM(C29:C31) -> 5607.99 | D32: =SUM(D29:D31) -> 5632 | E32: =SUM(E29:E31) -> 5625
A33: TOTAL EQUITY AND LIABILITIES | B33: =B23+B27+B32 -> 18734.86 | C33: =C23+C27+C32 -> 19484.21 | D33: =D23+D27+D32 -> 20343.97 | E33: =E23+E27+E32 -> 21196.576
A34: Balance Check (Assets - E&L) - should be zero | B34: =B18-B33 -> -95.33 | C34: =C18-C33 -> 3.98 | D34: =D18-D33 -> 8551.7927 | E34: =E18-E33 -> 6589.7314

Sheet Cash Flow
A1: Rail Vikas Nigam Limited - Cash Flow Statement
A2: Units: INR Crore | Indirect Method
A4: Particulars | B4: FY2024A | C4: FY2025A | D4: FY2026E | E4: FY2027E
A5: A. Cash Flow from Operating Activities
A6: Profit Before Tax | B6: ='Income Statement'!B19 -> 1939.4 | C6: ='Income Statement'!C19 -> 1550.17 | D6: ='Income Statement'!D19 -> 1580.6523 | E6: ='Income Statement'!E19 -> 1661.8061
A7: Add: Depreciation and Amortisation | B7: ='Income Statement'!B13 -> 20.82 | C7: ='Income Statement'!C13 -> 30.6 | D7: ='Income Statement'!D13 -> 33.048 | E7: ='Income Statement'!E13 -> 35.69184
A8: Add: Finance Costs | B8: ='Income Statement'!B12 -> 568.49 | C8: ='Income Statement'!C12 -> 539.51 | D8: ='Income Statement'!D12 -> 512.5345 | E8: ='Income Statement'!E12 -> 486.90777
A9: Less: Interest Income (Other Income) | B9: -1063.32 | C9: -874.53 | D9: -850 | E9: -830
A10: Working Capital Changes (Net) | B10: 2021.7 | C10: 1195.85 | D10: -200 | E10: -100
A11: Less: Income Tax Paid | B11: -453.73 | C11: -462.66 | D11: -380 | E11: -360
A12: Net Cash from Operating Activities (A) | B12: =SUM(B6:B11) -> 3033.36 | C12: =SUM(C6:C11) -> 1978.94 | D12: =SUM(D6:D11) -> 696.2348 | E12: =SUM(E6:E11) -> 894.40571
A13: B. Cash Flow from Investing Activities
A14: Purchase of Fixed Assets (Capex) | B14: =-Assumptions!B23 -> -377.29 | C14: =-Assumptions!C23 -> -472 | D14: =-Assumptions!D23 -> -472 | E14: =-Assumptions!E23 -> -400
A15: Investment in Subs / JVs | B15: -424.12 | C15: -143.65 | D15: -150 | E15: -150
A16: Interest and Dividend Received | B16: 310.97 | C16: 905.32 | D16: 870 | E16: 850
A17: Change in Bank Balances (FDs) | B17: -967.7 | C17: 1251.2 | D17: -200 | E17: -100
A18: Net Cash from Investing Activities (B) | B18: =SUM(B14:B17) -> -1458.14 | C18: =SUM(C14:C17) -> 1540.87 | D18: =SUM(D14:D17) -> 48 | E18: =SUM(E14:E17) -> 200
A19: C. Cash Flow from Financing Activities
A20: Repayment of Long-Term Borrowings | B20: =-Assumptions!B24 -> -439.94 | C20: =-Assumptions!C24 -> -358.62 | D20: =-Assumptions!D24 -> -358.62 | E20: =-Assumptions!E24 -> -400
A21: Interest Paid | B21: -441.52 | C21: -550.19 | D21: -520 | E21: -490
A22: Dividend Paid | B22: =-Assumptions!B25 -> 0 | C22: =-Assumptions!C25 -> 0 | D22: =-Assumptions!D25 -> 0 | E22: =-Assumptions!E25 -> 0
A23: Net Cash from Financing Activities (C) | B23: =SUM(B20:B22) -> -881.46 | C23: =SUM(C20:C22) -> -908.81 | D23: =SUM(D20:D22) -> -878.62 | E23: =SUM(E20:E22) -> -890
A24: Net Change in Cash (A+B+C) | B24: =B12+B18+B23 -> 693.76 | C24: =C12+C18+C23 -> 2611 | D24: =D12+D18+D23 -> -134.3852 | E24: =E12+E18+E23 -> 204.40571
A26: Opening Cash and Cash Equivalents | B26: 807.53 | C26: 1027.49 | D26: =C27 -> 3638.49 | E26: =D27 -> 3504.1048
A27: Closing Cash and Cash Equivalents | B27: =B24+B26 -> 1501.29 | C27: =C24+C26 -> 3638.49 | D27: =D24+D26 -> 3504.1048 | E27: =E24+E26 -> 3708.5105

Sheet Key Ratios
A1: Rail Vikas Nigam Limited - Key Financial Ratios
A3: Metric | B3: FY2024A | C3: FY2025A | D3: FY2026E | E3: FY2027E
A4: Profitability
A5: Revenue Growth % | B5: - | C5: =('Income Statement'!C6-'Income Statement'!B6)/'Income Statement'!B6 -> -0.085734413 | D5: =('Income Statement'!D6-'Income Statement'!C6)/'Income Statement'!C6 -> 0.05 | E5: =('Income Statement'!E6-'Income Statement'!D6)/'Income Statement'!D6 -> 0.08
A6: EBITDA Margin % | B6: ='Income Statement'!B17/'Income Statement'!B6 -> 0.11635572 | C6: ='Income Statement'!C17/'Income Statement'!C6 -> 0.10671109 | D6: ='Income Statement'!D17/'Income Statement'!D6 -> 0.10191504 | E6: ='Income Statement'!E17/'Income Statement'!E6 -> 0.096947494
A7: PBT Margin % | B7: ='Income Statement'!B20 -> 0.08923929 | C7: ='Income Statement'!C20 -> 0.078018154 | D7: ='Income Statement'!D20 -> 0.075764086 | E7: ='Income Statement'!E20 -> 0.073753669
A8: PAT Margin % | B8: ='Income Statement'!B23 -> 0.067315984 | C8: ='Income Statement'!C23 -> 0.059821786 | D8: ='Income Statement'!D23 -> 0.058111054 | E8: ='Income Statement'!E23 -> 0.056569064
A9: Effective Tax Rate % | B9: ='Income Statement'!B21/'Income Statement'!B19 -> 0.24566876 | C9: ='Income Statement'!C21/'Income Statement'!C19 -> 0.23323248 | D9: ='Income Statement'!D21/'Income Statement'!D19 -> 0.233 | E9: ='Income Statement'!E21/'Income Statement'!E19 -> 0.233
A10: Leverage and Solvency
A11: Debt-to-Equity (x) | B11: =('Balance Sheet'!B25+'Balance Sheet'!B29)/'Balance Sheet'!B23 -> 0.76109786 | C11: =('Balance Sheet'!C25+'Balance Sheet'!C29)/'Balance Sheet'!C23 -> 0.62490665 | D11: =('Balance Sheet'!D25+'Balance Sheet'!D29)/'Balance Sheet'!D23 -> 0.50836797 | E11: =('Balance Sheet'!E25+'Balance Sheet'!E29)/'Balance Sheet'!E23 -> 0.40742902
A12: Interest Coverage (x) | B12: ='Income Statement'!B17/'Income Statement'!B12 -> 4.4481169 | C12: ='Income Statement'!C17/'Income Statement'!C12 -> 3.9300106 | D12: ='Income Statement'!D17/'Income Statement'!D12 -> 4.1484716 | E12: ='Income Statement'!E17/'Income Statement'!E12 -> 4.4862822
A13: Net Debt (INR Cr) | B13: ='Balance Sheet'!B25+'Balance Sheet'!B29-'Balance Sheet'!B15 -> 4960.28 | C13: ='Balance Sheet'!C25+'Balance Sheet'!C29-'Balance Sheet'!C15 -> 2344.22 | D13: ='Balance Sheet'!D25+'Balance Sheet'!D29-'Balance Sheet'!D15 -> 5002.89 | E13: ='Balance Sheet'!E25+'Balance Sheet'!E29-'Balance Sheet'!E15 -> 4530.89
A14: Returns
A15: Return on Equity % (ROE) | B15: ='Income Statement'!B22/'Balance Sheet'!B23 -> 0.18595372 | C15: ='Income Statement'!C22/'Balance Sheet'!C23 -> 0.13783147 | D15: ='Income Statement'!D22/'Balance Sheet'!D23 -> 0.12319382 | E15: ='Income Statement'!E22/'Balance Sheet'!E23 -> 0.11461571
A16: Return on Assets % (ROA) | B16: ='Income Statement'!B22/'Balance Sheet'!B18 -> 0.078486421 | C16: ='Income Statement'!C22/'Balance Sheet'!C18 -> 0.060991811 | D16: ='Income Statement'!D22/'Balance Sheet'!D18 -> 0.041956335 | E16: ='Income Statement'!E22/'Balance Sheet'!E18 -> 0.045871705
A17: EPS - Basic (Rs.) | B17: ='Income Statement'!B27 -> 7.0164791 | C17: ='Income Statement'!C27 -> 5.7007604 | D17: ='Income Statement'!D27 -> 5.8146217 | E17: ='Income Statement'!E27 -> 6.1131558
